gradio_chessboard/__init__.py
gradio_chessboard/chessboard.py
gradio_chessboard/chessboard.pyi
gradio_chessboard/templates/component/Index-5gNR8bVr.js
gradio_chessboard/templates/component/_basePickBy-_H10dFuB.js
gradio_chessboard/templates/component/_baseUniq-DynaMQkd.js
gradio_chessboard/templates/component/arc-8FjXqVYo.js
gradio_chessboard/templates/component/architectureDiagram-IEHRJDOE-rVDoeiM3.js
gradio_chessboard/templates/component/blockDiagram-JOT3LUYC-Bb3ewVU6.js
gradio_chessboard/templates/component/c4Diagram-VJAJSXHY-B31x_aI4.js
gradio_chessboard/templates/component/channel-EVAlw0To.js
gradio_chessboard/templates/component/chunk-4BMEZGHF-D8_AAII-.js
gradio_chessboard/templates/component/chunk-A2AXSNBT-X4ZNlqk1.js
gradio_chessboard/templates/component/chunk-AEK57VVT-RTcsuDw6.js
gradio_chessboard/templates/component/chunk-D6G4REZN-FeVLPAYA.js
gradio_chessboard/templates/component/chunk-RZ5BOZE2-CpVegCmv.js
gradio_chessboard/templates/component/chunk-XZIHB7SX-Cv2mS0Ik.js
gradio_chessboard/templates/component/classDiagram-GIVACNV2-D7jXsGNH.js
gradio_chessboard/templates/component/classDiagram-v2-COTLJTTW-D7jXsGNH.js
gradio_chessboard/templates/component/clone-BIoa1DB2.js
gradio_chessboard/templates/component/cytoscape.esm-C2cgT2B2.js
gradio_chessboard/templates/component/dagre-OKDRZEBW-BIzNa1Ok.js
gradio_chessboard/templates/component/diagram-SSKATNLV-OTyuo5ts.js
gradio_chessboard/templates/component/diagram-VNBRO52H-J7LBsuEu.js
gradio_chessboard/templates/component/erDiagram-Q7BY3M3F-DJWvLVMr.js
gradio_chessboard/templates/component/flowDiagram-4HSFHLVR-SJTKAlwW.js
gradio_chessboard/templates/component/ganttDiagram-APWFNJXF-BCWN5Q1s.js
gradio_chessboard/templates/component/gitGraphDiagram-7IBYFJ6S-UAoCD0Dr.js
gradio_chessboard/templates/component/graph-cUBT2tcj.js
gradio_chessboard/templates/component/index.js
gradio_chessboard/templates/component/infoDiagram-PH2N3AL5-PLvUfFlQ.js
gradio_chessboard/templates/component/init-DjUOC4st.js
gradio_chessboard-0.0.10.dist-info/METADATA
gradio_chessboard-0.0.10.dist-info/WHEEL
gradio_chessboard-0.0.10.dist-info/RECORD
